karvi/__init__.py
karvi/admin.py
karvi/apps.py
karvi/assets/js/karvi.js
karvi/assets/js/plugins/carousel.js
karvi/assets/js/plugins/navbar.js
karvi/assets/js/plugins/selectr.js
karvi/assets/package.json
karvi/assets/sass/_variables.sass
karvi/assets/sass/karvi.sass
karvi/assets/ts/karvi.ts
karvi/assets/ts/utils/navbar.ts
karvi/assets/ts/utils/selectex.ts
karvi/assets/tsconfig.json
karvi/assets/webpack.mix.js
karvi/assets/yarn.lock
karvi/forms.py
karvi/migrations/__init__.py
karvi/models.py
karvi/static/karvi/css/karvi.css
karvi/static/karvi/js/karvi.js
karvi/static/karvi/js/karvi.js.LICENSE.txt
karvi/templates/karvi/addons/alerts.html
karvi/templates/karvi/base/__2col.html
karvi/templates/karvi/base/__base.html
karvi/templates/karvi/base/__messages.html
karvi/templates/karvi/base/__pagination.html
karvi/templates/karvi/navbar/__base.html
karvi/templates/karvi/navbar/__user.html
karvi/templates/registration/logged_out.html
karvi/templates/registration/login.html
karvi/templates/registration/password_reset_complete.html
karvi/templates/registration/password_reset_confirm.html
karvi/templates/registration/password_reset_done.html
karvi/templates/registration/password_reset_email.html
karvi/templates/registration/password_reset_form.html
karvi/templates/registration/signup.html
karvi/templatetags/__init__.py
karvi/templatetags/karvi.py
karvi/templatetags/karvi_alerts.py
karvi/templatetags/karvi_style.py
karvi/tests/__init__.py
karvi/tests/utils/path.py
karvi/urls.py
karvi/utils/__init__.py
karvi/utils/enum.py
karvi/utils/path.py
karvi/utils/settings.py
karvi/views.py
karvi/widgets/__init__.py
karvi/widgets/selectex.py
karvi/widgets/selectr.py
karvi-0.4.0.dist-info/LICENSE
karvi-0.4.0.dist-info/WHEEL
karvi-0.4.0.dist-info/METADATA
karvi-0.4.0.dist-info/RECORD
